bagle/__init__.py
bagle/data.py
bagle/fake_data.py
bagle/frame_convert.py
bagle/model.py
bagle/model_fitter.py
bagle/multinest_utils.py
bagle/orbits.py
bagle/parallax.py
bagle/plot_models.py
bagle/sensitivity.py
bagle/dynesty/plotting.py
bagle/dynesty/results.py
bagle/dynesty/utils.py
bagle-1.0.0.dist-info/licenses/LICENSE
bagle-1.0.0.dist-info/licenses/LICENSE.txt
bagle-1.0.0.dist-info/METADATA
bagle-1.0.0.dist-info/WHEEL
bagle-1.0.0.dist-info/top_level.txt
bagle-1.0.0.dist-info/RECORD
