Metadata-Version: 2.4
Name: BAGLE
Version: 1.0.0
Summary: BAGLE (Bayesian Analysis of Gravitational Lensing Events) is a package to model and fit microlensing events.
Author: T. Dex Bhadra, Michael Medford, Casey Lam, Macy Huston, Edward Broadberry, Jeff Chen, Andrew Scharf, Sean Terry, Nijaid Arredondo
Author-email: Jessica Lu <jlu.astro@berkeley.edu>
License-Expression: GPL-3.0-or-later
Project-URL: Homepage, https://github.com/MovingUniverseLab/BAGLE_Microlensing
Project-URL: Issues, https://github.com/MovingUniverseLab/BAGLE_Microlensing/issues
Classifier: Development Status :: 5 - Production/Stable
Classifier: Programming Language :: Python :: 3.11
Classifier: Operating System :: OS Independent
Classifier: Intended Audience :: Developers
Requires-Python: >=3.11
License-File: LICENSE
License-File: LICENSE.txt
Requires-Dist: numpy>=1.24
Requires-Dist: pymultinest
Requires-Dist: matplotlib
Requires-Dist: astropy>=5.3
Requires-Dist: celerite>=0.4.2
Requires-Dist: scipy>=1.10
Dynamic: license-file
